README.md
setup.py
odmd/__init__.py
odmd/_online.py
odmd/_window.py
odmd.egg-info/PKG-INFO
odmd.egg-info/SOURCES.txt
odmd.egg-info/dependency_links.txt
odmd.egg-info/requires.txt
odmd.egg-info/top_level.txt