Metadata-Version: 2.1
Name: odmd
Version: 0.1.3
Summary: Online and Window Dynamic Mode Decomposition algorithms
Home-page: https://github.com/haozhg/odmd
Author: Hao Zhang
Author-email: haozhang@alumni.princeton.edu
License: MIT
Platform: UNKNOWN
Classifier: License :: OSI Approved :: MIT License
Classifier: Programming Language :: Python :: 3
Classifier: Programming Language :: Python :: 3.7
